wm_ssim/__init__.py
wm_ssim/compress.py
wm_ssim/get_object_data.py
wm_ssim/helper_functions.py
wm_ssim/util.py
wm_ssim-0.1.dist-info/DESCRIPTION.rst
wm_ssim-0.1.dist-info/METADATA
wm_ssim-0.1.dist-info/RECORD
wm_ssim-0.1.dist-info/WHEEL
wm_ssim-0.1.dist-info/metadata.json
wm_ssim-0.1.dist-info/top_level.txt
