Metadata-Version: 2.0
Name: wm-ssim
Version: 0.1
Summary: The library to find WM_SSIM of a webapge with all the transformations
Home-page: http://github.com/abdul-manaan/wm_ssim
Author: Abdul Manan
Author-email: manan.lums@gmail.com
License: MIT
Platform: UNKNOWN
Classifier: Programming Language :: Python :: 2
Requires-Dist: Pillow (==6.1.0)
Requires-Dist: beautifulsoup4 (==4.8.0)
Requires-Dist: matplotlib (==3.0.3)
Requires-Dist: numpy (==1.11.0)
Requires-Dist: opencv-python (==4.1.1.26)
Requires-Dist: python-magic (==0.4.15)
Requires-Dist: pyvirtualdisplay (==0.2.4)
Requires-Dist: scikit-image (==0.15.0)
Requires-Dist: selenium (==3.141.0)
Requires-Dist: skimage (==0.0)
